LICENSE
README.md
pyproject.toml
setup.py
quotect/__init__.py
quotect/pipeline.py
quotect/predict.py
quotect/train.py
quotect.egg-info/PKG-INFO
quotect.egg-info/SOURCES.txt
quotect.egg-info/dependency_links.txt
quotect.egg-info/requires.txt
quotect.egg-info/top_level.txt
quotect/common/arguments.py
quotect/common/constants.py
quotect/data/convert_quotes.py
quotect/data/data.py
quotect/data/eval_quotes.py
quotect/data/preprocess_data.py
quotect/model/__init__.py
quotect/model/logits_processor.py
quotect/model/model.py
quotect/model/trainer.py
quotect/utils/alignment.py
quotect/utils/helper.py