Metadata-Version: 2.2
Name: quotect
Version: 1.0.0
Summary: state-of-the-art, ready to use software for quotation detection in German texts
Author: Fynn Petersen-Frey
License: MIT
Project-URL: Repository, https://github.com/fynnos/quotect.git
Requires-Python: >=3.10
License-File: LICENSE
Requires-Dist: accelerate
Requires-Dist: transformers[torch]
Requires-Dist: torch
Requires-Dist: argparse_dataclass
Requires-Dist: sentencepiece
Requires-Dist: scipy
Requires-Dist: numpy
Requires-Dist: protobuf
Requires-Dist: spacy
